README
setup.py
Xeu/__init__.py
Xeu.egg-info/PKG-INFO
Xeu.egg-info/SOURCES.txt
Xeu.egg-info/dependency_links.txt
Xeu.egg-info/entry_points.txt
Xeu.egg-info/requires.txt
Xeu.egg-info/top_level.txt
Xeu/configure/__init__.py
Xeu/configure/base.py
Xeu/configure/collection.py
Xeu/configure/init.py
Xeu/configure/test_init.py
Xeu/connector/__base.py
Xeu/connector/__init__.py
Xeu/connector/kafka.py
Xeu/connector/mysql.py
Xeu/connector/redis.py
Xeu/core/__init__.py
Xeu/core/loader/AppLoading.py
Xeu/core/loader/ApplicationCore.py
Xeu/core/loader/__RootApplication.py
Xeu/core/loader/__init__.py
Xeu/core/route/RouterCore.py
Xeu/core/route/RouterGroup.py
Xeu/core/route/__init__.py
Xeu/daemon/__init__.py
Xeu/logger/__init__.py
Xeu/logger/conf.py
Xeu/setup/__init__.py
Xeu/setup/script/__init__.py
Xeu/setup/script/manage.py
Xeu/task/__init__.py
Xeu/task/kafka_task.py
Xeu/task/redis_task.py
Xeu/task/task_base.py
Xeu/task/task_client.py
Xeu/task/task_server.py
Xeu/task/test_redis_task.py
Xeu/utils/CommonException.py
Xeu/utils/DevConsole.py
Xeu/utils/MiddlewareSetup.py
Xeu/utils/ResponseCodeManage.py
Xeu/utils/__init__.py
Xeu/utils/config/TomlTool.py
Xeu/utils/config/__init__.py
Xeu/utils/config/base.py
configure/AppConfig.py
configure/SystemConfig.py
configure/__init__.py
dao/__init__.py